{
	"dictionary": [
		{
			"english": "mention",
			"romanized": "kanehistodi"
		},
		{
			"english": "menu",
			"romanized": "asehihi agisdi"
		},
		{
			"english": "mercantile",
			"romanized": "adananv"
		},
		{
			"english": "merchant",
			"romanized": "udanani"
		},
		{
			"english": "metal",
			"romanized": "talugisgi"
		},
		{
			"english": "meter, counter",
			"romanized": "asehihi"
		},
		{
			"english": "method",
			"romanized": "igvnedi"
		},
		{
			"english": "Mexican, people",
			"romanized": "anisquani"
		},
		{
			"english": "mice",
			"romanized": "tsidetsi"
		},
		{
			"english": "middle",
			"romanized": "ayeli"
		},
		{
			"english": "midday",
			"romanized": "iga"
		},
		{
			"english": "midway",
			"romanized": "ayeli iyv"
		},
		{
			"english": "might, strength",
			"romanized": "nulinigvgv"
		},
		{
			"english": "might, maybe",
			"romanized": "yigaquu"
		},
		{
			"english": "mighty, strength",
			"romanized": "wulinigvgv"
		},
		{
			"english": "mild",
			"romanized": "wanigala"
		},
		{
			"english": "mile",
			"romanized": "sutlilodv"
		},
		{
			"english": "military",
			"romanized": "aniyosgii"
		},
		{
			"english": "milk",
			"romanized": "unvdi"
		},
		{
			"english": "mill",
			"romanized": "stosgiyi"
		},
		{
			"english": "million",
			"romanized": "iyuquadinvda"
		},
		{
			"english": "millions",
			"romanized": "itsuquadinvda"
		},
		{
			"english": "mind, heart",
			"romanized": "oda(nv)dv"
		},
		{
			"english": "mine, possession",
			"romanized": "aquatseli"
		},
		{
			"english": "minister",
			"romanized": "a(li)tsadohvsgi"
		},
		{
			"english": "ministers",
			"romanized": "ana(li)tsadohvsgi"
		},
		{
			"english": "mink",
			"romanized": "etli"
		},
		{
			"english": "minnow",
			"romanized": "usdi atsadi"
		},
		{
			"english": "minute",
			"romanized": "i(ga)tawastanv"
		},
		{
			"english": "miracle",
			"romanized": "usquani(go)di"
		},
		{
			"english": "mirror",
			"romanized": "adagedi"
		},
		{
			"english": "miscellaneous",
			"romanized": "tsudalenvda"
		},
		{
			"english": "miserable",
			"romanized": "utsosedi"
		},
		{
			"english": "miss, fail to hit",
			"romanized": "ganvdisdi"
		},
		{
			"english": "missing, person",
			"romanized": "anatloga"
		},
		{
			"english": "missionary",
			"romanized": "kanohedv atsinvsida"
		},
		{
			"english": "misting",
			"romanized": "kanuyoladia"
		},
		{
			"english": "mistake",
			"romanized": "galidastodi"
		},
		{
			"english": "mistaken",
			"romanized": "galidastanv"
		},
		{
			"english": "mitten",
			"romanized": "a(li)yesulo"
		}
	]
}
